mandos/lib/libCore.so
mandos/lib/libhwloc.so
mandos/lib/libhwloc.so.15
mandos/lib/libhwloc.so.15.6.4
mandos/lib/libtbb.so
mandos/lib/libtbb.so.12
mandos/lib/libtbb.so.12.10
mandos/lib/libtbbbind_2_5.so
mandos/lib/libtbbbind_2_5.so.3
mandos/lib/libtbbbind_2_5.so.3.10
mandos/lib/libtbbmalloc.so
mandos/lib/libtbbmalloc.so.2
mandos/lib/libtbbmalloc.so.2.10
mandos/lib/libtbbmalloc_proxy.so
mandos/lib/libtbbmalloc_proxy.so.2
mandos/lib/libtbbmalloc_proxy.so.2.10
mandos/mandos_cpp.cpython-312-x86_64-linux-gnu.so
mandos_sim/__init__.py
mandos_sim/parallel_transport.py
mandos_sim-0.0.0.dist-info/METADATA
mandos_sim-0.0.0.dist-info/WHEEL
mandos_sim-0.0.0.dist-info/licenses/LICENSE
mandos_sim-0.0.0.dist-info/licenses/AUTHORS
mandos_sim-0.0.0.dist-info/RECORD
