Metadata-Version: 2.1
Name: mandos-sim
Version: 0.0.0
Summary: Mandos: A general purpose physically based simulation engine.
Author-Email: Juan Jose Casafranca <jjcasmar@gmail.com>
Maintainer-Email: Juan Jose Casafranca <jjcasmar@gmail.com>
License: MIT License
Classifier: Development Status :: 5 - Production/Stable
Classifier: License :: OSI Approved :: MIT License
Classifier: Programming Language :: Python :: 3
Project-URL: Homepage, https://gitlab.com/mslab-urjc/mandos
Requires-Python: >=3.7
Requires-Dist: numpy
Requires-Dist: polyscope
Requires-Dist: scipy
